{"sections":{"main":{"type":"template--cart","settings":{}},"rich-text":{"type":"text--rich-text","disabled":true,"settings":{"colors":"dark","title":"Welcome to our store","text":"<p>Use this text block to show store announcements, advertise products and collections, or simply welcome visitors to your store.<\/p>","button_label":"","button_link":""}},"b3f8bcc3-7194-451f-8fa2-341b287bc04b":{"type":"collection--featured-collection","settings":{"colors":"white","title":"You may also like","richtext":"","collection":"kitchen-products","grid-desktop":4,"grid-tablet":3,"grid-mobile":2,"rows":1,"hover-effect":false,"show-vendor":false,"show_view_all":false}}},"order":["main","rich-text","b3f8bcc3-7194-451f-8fa2-341b287bc04b"]}